insight/__init__.py
insight/admin.py
insight/apps.py
insight/forms.py
insight/managers.py
insight/middleware.py
insight/models.py
insight/tests.py
insight/urls.py
insight/views.py
insight/__pycache__/__init__.cpython-311.pyc
insight/__pycache__/admin.cpython-311.pyc
insight/__pycache__/apps.cpython-311.pyc
insight/__pycache__/forms.cpython-311.pyc
insight/__pycache__/managers.cpython-311.pyc
insight/__pycache__/middleware.cpython-311.pyc
insight/__pycache__/models.cpython-311.pyc
insight/__pycache__/tests.cpython-311.pyc
insight/__pycache__/urls.cpython-311.pyc
insight/__pycache__/views.cpython-311.pyc
insight/migrations/0001_initial.py
insight/migrations/__init__.py
insight/migrations/__pycache__/0001_initial.cpython-311.pyc
insight/migrations/__pycache__/0002_pageview_created_at.cpython-311.pyc
insight/migrations/__pycache__/0002_pageview_view_name.cpython-311.pyc
insight/migrations/__pycache__/0002_remove_visitor_time_on_site.cpython-311.pyc
insight/migrations/__pycache__/0003_remove_pageview_view_name.cpython-311.pyc
insight/migrations/__pycache__/0003_remove_visitor_ip_address_remove_visitor_user_agent.cpython-311.pyc
insight/migrations/__pycache__/0003_visitor_end_time_visitor_expiry_age_and_more.cpython-311.pyc
insight/migrations/__pycache__/0004_alter_pageview_options_apirequest.cpython-311.pyc
insight/migrations/__pycache__/0004_pageview_path.cpython-311.pyc
insight/migrations/__pycache__/__init__.cpython-311.pyc
insight/static/insight/css/punkweb.css
insight/static/insight/vendor/punkweb-ui.min.css
insight/templates/insight/base.html
insight/templates/insight/index.html
insight/templates/insight/page_stats_detail.html
insight/templates/insight/page_stats_index.html
insight/templates/insight/page_view_detail.html
insight/templates/insight/page_view_index.html
insight/templates/insight/referrer_stats_detail.html
insight/templates/insight/referrer_stats_index.html
insight/templates/insight/visitor_detail.html
insight/templates/insight/visitor_history.html
punkweb_insight-0.1.1.dist-info/LICENSE
punkweb_insight-0.1.1.dist-info/METADATA
punkweb_insight-0.1.1.dist-info/WHEEL
punkweb_insight-0.1.1.dist-info/top_level.txt
punkweb_insight-0.1.1.dist-info/RECORD
