Metadata-Version: 2.1
Name: punkweb-insight
Version: 0.1.1
Summary: Django application that provides visitor and page view tracking and an analytics dashboard for your Django website.
Home-page: https://github.com/Punkweb/punkweb-insight
Author: Punkweb
Author-email: punkwebnet@gmail.com
License: BSD-3-Clause
Classifier: Environment :: Web Environment
Classifier: Framework :: Django
Classifier: Intended Audience :: Developers
Classifier: License :: OSI Approved :: BSD License
Classifier: Operating System :: OS Independent
Classifier: Programming Language :: Python
Classifier: Programming Language :: Python :: 3
License-File: LICENSE
Requires-Dist: django >=4.0
